Metadata-Version: 1.1
Name: django-monitor-psutil
Version: 0.0.1
Summary: Monitor exposes a JSON endpoint to your system to check on system information
Home-page: https://github.com/emman27/djangomonitor
Author: Emmanuel Goh
Author-email: emmanuel.goh.7@gmail.com
License: MIT License
Platform: UNKNOWN
Classifier: Environment :: Web Environment
Classifier: Framework :: Django
Classifier: Framework :: Django :: 1.11
Classifier: Intended Audience :: Developers
Classifier: License :: OSI Approved :: MIT License
Classifier: Operating System :: OS Independent
Classifier: Programming Language :: Python
Classifier: Programming Language :: Python :: 3
Classifier: Programming Language :: Python :: 3.4
Classifier: Programming Language :: Python :: 3.5
Classifier: Topic :: Internet :: WWW/HTTP
Classifier: Topic :: Internet :: WWW/HTTP :: Dynamic Content
